joinpython/__init__.py
joinpython-1.0.2.data/scripts/join.py
joinpython-1.0.2.dist-info/LICENSE
joinpython-1.0.2.dist-info/METADATA
joinpython-1.0.2.dist-info/WHEEL
joinpython-1.0.2.dist-info/top_level.txt
joinpython-1.0.2.dist-info/RECORD
