Metadata-Version: 2.1
Name: joinpython
Version: 1.0.2
Summary: A python script that allows for pushing to Join by Joaoapps from the command line.
Home-page: https://github.com/Rayquaza01/JoinPython
Author: Rayquaza01
Author-email: rayquaza01@outlook.com
License: MIT
Platform: UNKNOWN
Classifier: Programming Language :: Python :: 3
Classifier: License :: OSI Approved :: MIT License
Classifier: Operating System :: OS Independent
